{
  "generated_at": "2026-05-30T17:00:51.981560+00:00",
  "mode": "real",
  "covered_months": [
    "2025-01",
    "2026-04"
  ],
  "month_count": 16,
  "months": [
    "2025-01",
    "2025-02",
    "2025-03",
    "2025-04",
    "2025-05",
    "2025-06",
    "2025-07",
    "2025-08",
    "2025-09",
    "2025-10",
    "2025-11",
    "2025-12",
    "2026-01",
    "2026-02",
    "2026-03",
    "2026-04"
  ],
  "sources": [
    "yellow",
    "green",
    "hvfhv"
  ],
  "source_labels": {
    "all": "All Services",
    "yellow": "Yellow Taxi",
    "green": "Green Taxi",
    "hvfhv": "HVFHV"
  },
  "raw_file_count": 48,
  "raw_size_bytes": 9089009098,
  "taxi_zone_count": 263,
  "totals": {
    "raw_record_count": 391817992,
    "time_clean_record_count": 391101240,
    "od_clean_record_count": 349525012,
    "outside_month_rows": 561,
    "nonpositive_duration_rows": 715717,
    "duration_over_24h_rows": 475,
    "invalid_pickup_zone_rows": 225948,
    "invalid_dropoff_zone_rows": 15113402,
    "nonpositive_distance_rows": 1933798,
    "distance_over_100_rows": 32653,
    "negative_fare_rows": 3010791,
    "fare_over_500_rows": 9607
  },
  "by_source": [
    {
      "source": "green",
      "raw_record_count": 757466,
      "time_clean_record_count": 755134,
      "od_clean_record_count": 665094
    },
    {
      "source": "hvfhv",
      "raw_record_count": 327460054,
      "time_clean_record_count": 327446414,
      "od_clean_record_count": 289226756
    },
    {
      "source": "yellow",
      "raw_record_count": 63600472,
      "time_clean_record_count": 62899692,
      "od_clean_record_count": 59633162
    }
  ],
  "by_source_month": [
    {
      "source": "green",
      "month": "2025-01",
      "raw_record_count": 48326,
      "outside_month_rows": 43,
      "nonpositive_duration_rows": 48,
      "duration_over_24h_rows": 0,
      "invalid_pickup_zone_rows": 129,
      "invalid_dropoff_zone_rows": 607,
      "nonpositive_distance_rows": 2671,
      "distance_over_100_rows": 22,
      "negative_fare_rows": 150,
      "fare_over_500_rows": 0
    },
    {
      "source": "green",
      "month": "2025-02",
      "raw_record_count": 46621,
      "outside_month_rows": 19,
      "nonpositive_duration_rows": 257,
      "duration_over_24h_rows": 0,
      "invalid_pickup_zone_rows": 156,
      "invalid_dropoff_zone_rows": 611,
      "nonpositive_distance_rows": 2377,
      "distance_over_100_rows": 19,
      "negative_fare_rows": 162,
      "fare_over_500_rows": 2
    },
    {
      "source": "green",
      "month": "2025-03",
      "raw_record_count": 51539,
      "outside_month_rows": 11,
      "nonpositive_duration_rows": 371,
      "duration_over_24h_rows": 1,
      "invalid_pickup_zone_rows": 199,
      "invalid_dropoff_zone_rows": 723,
      "nonpositive_distance_rows": 2765,
      "distance_over_100_rows": 17,
      "negative_fare_rows": 155,
      "fare_over_500_rows": 0
    },
    {
      "source": "green",
      "month": "2025-04",
      "raw_record_count": 52132,
      "outside_month_rows": 12,
      "nonpositive_duration_rows": 351,
      "duration_over_24h_rows": 0,
      "invalid_pickup_zone_rows": 163,
      "invalid_dropoff_zone_rows": 724,
      "nonpositive_distance_rows": 2922,
      "distance_over_100_rows": 20,
      "negative_fare_rows": 133,
      "fare_over_500_rows": 0
    },
    {
      "source": "green",
      "month": "2025-05",
      "raw_record_count": 55399,
      "outside_month_rows": 10,
      "nonpositive_duration_rows": 332,
      "duration_over_24h_rows": 0,
      "invalid_pickup_zone_rows": 179,
      "invalid_dropoff_zone_rows": 849,
      "nonpositive_distance_rows": 2781,
      "distance_over_100_rows": 22,
      "negative_fare_rows": 175,
      "fare_over_500_rows": 2
    },
    {
      "source": "green",
      "month": "2025-06",
      "raw_record_count": 49390,
      "outside_month_rows": 16,
      "nonpositive_duration_rows": 314,
      "duration_over_24h_rows": 0,
      "invalid_pickup_zone_rows": 174,
      "invalid_dropoff_zone_rows": 823,
      "nonpositive_distance_rows": 1818,
      "distance_over_100_rows": 9,
      "negative_fare_rows": 156,
      "fare_over_500_rows": 1
    },
    {
      "source": "green",
      "month": "2025-07",
      "raw_record_count": 48205,
      "outside_month_rows": 13,
      "nonpositive_duration_rows": 40,
      "duration_over_24h_rows": 0,
      "invalid_pickup_zone_rows": 175,
      "invalid_dropoff_zone_rows": 730,
      "nonpositive_distance_rows": 1516,
      "distance_over_100_rows": 15,
      "negative_fare_rows": 130,
      "fare_over_500_rows": 1
    },
    {
      "source": "green",
      "month": "2025-08",
      "raw_record_count": 46306,
      "outside_month_rows": 23,
      "nonpositive_duration_rows": 38,
      "duration_over_24h_rows": 0,
      "invalid_pickup_zone_rows": 234,
      "invalid_dropoff_zone_rows": 929,
      "nonpositive_distance_rows": 1461,
      "distance_over_100_rows": 12,
      "negative_fare_rows": 132,
      "fare_over_500_rows": 2
    },
    {
      "source": "green",
      "month": "2025-09",
      "raw_record_count": 48893,
      "outside_month_rows": 33,
      "nonpositive_duration_rows": 51,
      "duration_over_24h_rows": 0,
      "invalid_pickup_zone_rows": 177,
      "invalid_dropoff_zone_rows": 848,
      "nonpositive_distance_rows": 1448,
      "distance_over_100_rows": 12,
      "negative_fare_rows": 114,
      "fare_over_500_rows": 7
    },
    {
      "source": "green",
      "month": "2025-10",
      "raw_record_count": 49416,
      "outside_month_rows": 21,
      "nonpositive_duration_rows": 29,
      "duration_over_24h_rows": 0,
      "invalid_pickup_zone_rows": 182,
      "invalid_dropoff_zone_rows": 773,
      "nonpositive_distance_rows": 1605,
      "distance_over_100_rows": 17,
      "negative_fare_rows": 128,
      "fare_over_500_rows": 3
    },
    {
      "source": "green",
      "month": "2025-11",
      "raw_record_count": 46912,
      "outside_month_rows": 21,
      "nonpositive_duration_rows": 43,
      "duration_over_24h_rows": 0,
      "invalid_pickup_zone_rows": 120,
      "invalid_dropoff_zone_rows": 651,
      "nonpositive_distance_rows": 1494,
      "distance_over_100_rows": 21,
      "negative_fare_rows": 142,
      "fare_over_500_rows": 3
    },
    {
      "source": "green",
      "month": "2025-12",
      "raw_record_count": 48236,
      "outside_month_rows": 26,
      "nonpositive_duration_rows": 36,
      "duration_over_24h_rows": 1,
      "invalid_pickup_zone_rows": 138,
      "invalid_dropoff_zone_rows": 715,
      "nonpositive_distance_rows": 1580,
      "distance_over_100_rows": 23,
      "negative_fare_rows": 159,
      "fare_over_500_rows": 5
    },
    {
      "source": "green",
      "month": "2026-01",
      "raw_record_count": 40272,
      "outside_month_rows": 22,
      "nonpositive_duration_rows": 29,
      "duration_over_24h_rows": 0,
      "invalid_pickup_zone_rows": 134,
      "invalid_dropoff_zone_rows": 633,
      "nonpositive_distance_rows": 1290,
      "distance_over_100_rows": 7,
      "negative_fare_rows": 119,
      "fare_over_500_rows": 1
    },
    {
      "source": "green",
      "month": "2026-02",
      "raw_record_count": 37373,
      "outside_month_rows": 11,
      "nonpositive_duration_rows": 25,
      "duration_over_24h_rows": 0,
      "invalid_pickup_zone_rows": 125,
      "invalid_dropoff_zone_rows": 582,
      "nonpositive_distance_rows": 1388,
      "distance_over_100_rows": 12,
      "negative_fare_rows": 106,
      "fare_over_500_rows": 0
    },
    {
      "source": "green",
      "month": "2026-03",
      "raw_record_count": 44208,
      "outside_month_rows": 9,
      "nonpositive_duration_rows": 35,
      "duration_over_24h_rows": 0,
      "invalid_pickup_zone_rows": 143,
      "invalid_dropoff_zone_rows": 660,
      "nonpositive_distance_rows": 1428,
      "distance_over_100_rows": 11,
      "negative_fare_rows": 111,
      "fare_over_500_rows": 4
    },
    {
      "source": "green",
      "month": "2026-04",
      "raw_record_count": 44238,
      "outside_month_rows": 3,
      "nonpositive_duration_rows": 38,
      "duration_over_24h_rows": 0,
      "invalid_pickup_zone_rows": 150,
      "invalid_dropoff_zone_rows": 738,
      "nonpositive_distance_rows": 1604,
      "distance_over_100_rows": 9,
      "negative_fare_rows": 153,
      "fare_over_500_rows": 5
    },
    {
      "source": "hvfhv",
      "month": "2025-01",
      "raw_record_count": 20405666,
      "outside_month_rows": 0,
      "nonpositive_duration_rows": 4,
      "duration_over_24h_rows": 0,
      "invalid_pickup_zone_rows": 5048,
      "invalid_dropoff_zone_rows": 819492,
      "nonpositive_distance_rows": 2606,
      "distance_over_100_rows": 1480,
      "negative_fare_rows": 2427,
      "fare_over_500_rows": 265
    },
    {
      "source": "hvfhv",
      "month": "2025-02",
      "raw_record_count": 19339461,
      "outside_month_rows": 0,
      "nonpositive_duration_rows": 4,
      "duration_over_24h_rows": 0,
      "invalid_pickup_zone_rows": 4780,
      "invalid_dropoff_zone_rows": 808214,
      "nonpositive_distance_rows": 2469,
      "distance_over_100_rows": 1279,
      "negative_fare_rows": 518,
      "fare_over_500_rows": 231
    },
    {
      "source": "hvfhv",
      "month": "2025-03",
      "raw_record_count": 20536879,
      "outside_month_rows": 0,
      "nonpositive_duration_rows": 4,
      "duration_over_24h_rows": 0,
      "invalid_pickup_zone_rows": 5037,
      "invalid_dropoff_zone_rows": 911641,
      "nonpositive_distance_rows": 2185,
      "distance_over_100_rows": 1531,
      "negative_fare_rows": 382,
      "fare_over_500_rows": 380
    },
    {
      "source": "hvfhv",
      "month": "2025-04",
      "raw_record_count": 19753983,
      "outside_month_rows": 0,
      "nonpositive_duration_rows": 3,
      "duration_over_24h_rows": 0,
      "invalid_pickup_zone_rows": 5413,
      "invalid_dropoff_zone_rows": 880080,
      "nonpositive_distance_rows": 2327,
      "distance_over_100_rows": 1437,
      "negative_fare_rows": 345,
      "fare_over_500_rows": 338
    },
    {
      "source": "hvfhv",
      "month": "2025-05",
      "raw_record_count": 21091193,
      "outside_month_rows": 0,
      "nonpositive_duration_rows": 7,
      "duration_over_24h_rows": 0,
      "invalid_pickup_zone_rows": 5897,
      "invalid_dropoff_zone_rows": 977684,
      "nonpositive_distance_rows": 2785,
      "distance_over_100_rows": 1800,
      "negative_fare_rows": 327,
      "fare_over_500_rows": 492
    },
    {
      "source": "hvfhv",
      "month": "2025-06",
      "raw_record_count": 19868009,
      "outside_month_rows": 0,
      "nonpositive_duration_rows": 1,
      "duration_over_24h_rows": 0,
      "invalid_pickup_zone_rows": 6084,
      "invalid_dropoff_zone_rows": 934415,
      "nonpositive_distance_rows": 2500,
      "distance_over_100_rows": 2216,
      "negative_fare_rows": 487,
      "fare_over_500_rows": 591
    },
    {
      "source": "hvfhv",
      "month": "2025-07",
      "raw_record_count": 19653012,
      "outside_month_rows": 0,
      "nonpositive_duration_rows": 1,
      "duration_over_24h_rows": 0,
      "invalid_pickup_zone_rows": 6357,
      "invalid_dropoff_zone_rows": 932340,
      "nonpositive_distance_rows": 2155,
      "distance_over_100_rows": 2607,
      "negative_fare_rows": 470,
      "fare_over_500_rows": 791
    },
    {
      "source": "hvfhv",
      "month": "2025-08",
      "raw_record_count": 19271461,
      "outside_month_rows": 0,
      "nonpositive_duration_rows": 1,
      "duration_over_24h_rows": 0,
      "invalid_pickup_zone_rows": 6953,
      "invalid_dropoff_zone_rows": 926078,
      "nonpositive_distance_rows": 2220,
      "distance_over_100_rows": 2590,
      "negative_fare_rows": 772,
      "fare_over_500_rows": 779
    },
    {
      "source": "hvfhv",
      "month": "2025-09",
      "raw_record_count": 19434641,
      "outside_month_rows": 0,
      "nonpositive_duration_rows": 3,
      "duration_over_24h_rows": 0,
      "invalid_pickup_zone_rows": 5980,
      "invalid_dropoff_zone_rows": 953714,
      "nonpositive_distance_rows": 2177,
      "distance_over_100_rows": 1893,
      "negative_fare_rows": 1042,
      "fare_over_500_rows": 629
    },
    {
      "source": "hvfhv",
      "month": "2025-10",
      "raw_record_count": 21308701,
      "outside_month_rows": 0,
      "nonpositive_duration_rows": 3,
      "duration_over_24h_rows": 0,
      "invalid_pickup_zone_rows": 5717,
      "invalid_dropoff_zone_rows": 994442,
      "nonpositive_distance_rows": 2263,
      "distance_over_100_rows": 1959,
      "negative_fare_rows": 1765,
      "fare_over_500_rows": 589
    },
    {
      "source": "hvfhv",
      "month": "2025-11",
      "raw_record_count": 20818240,
      "outside_month_rows": 0,
      "nonpositive_duration_rows": 12211,
      "duration_over_24h_rows": 0,
      "invalid_pickup_zone_rows": 6101,
      "invalid_dropoff_zone_rows": 970659,
      "nonpositive_distance_rows": 2084,
      "distance_over_100_rows": 1841,
      "negative_fare_rows": 1940,
      "fare_over_500_rows": 537
    },
    {
      "source": "hvfhv",
      "month": "2025-12",
      "raw_record_count": 22108438,
      "outside_month_rows": 0,
      "nonpositive_duration_rows": 4,
      "duration_over_24h_rows": 0,
      "invalid_pickup_zone_rows": 6979,
      "invalid_dropoff_zone_rows": 1010432,
      "nonpositive_distance_rows": 2357,
      "distance_over_100_rows": 1764,
      "negative_fare_rows": 3020,
      "fare_over_500_rows": 676
    },
    {
      "source": "hvfhv",
      "month": "2026-01",
      "raw_record_count": 20940373,
      "outside_month_rows": 0,
      "nonpositive_duration_rows": 738,
      "duration_over_24h_rows": 0,
      "invalid_pickup_zone_rows": 6352,
      "invalid_dropoff_zone_rows": 853090,
      "nonpositive_distance_rows": 2782,
      "distance_over_100_rows": 1627,
      "negative_fare_rows": 29965,
      "fare_over_500_rows": 492
    },
    {
      "source": "hvfhv",
      "month": "2026-02",
      "raw_record_count": 19875686,
      "outside_month_rows": 0,
      "nonpositive_duration_rows": 124,
      "duration_over_24h_rows": 0,
      "invalid_pickup_zone_rows": 5884,
      "invalid_dropoff_zone_rows": 826708,
      "nonpositive_distance_rows": 2020,
      "distance_over_100_rows": 1552,
      "negative_fare_rows": 4145,
      "fare_over_500_rows": 525
    },
    {
      "source": "hvfhv",
      "month": "2026-03",
      "raw_record_count": 22058358,
      "outside_month_rows": 0,
      "nonpositive_duration_rows": 503,
      "duration_over_24h_rows": 0,
      "invalid_pickup_zone_rows": 6631,
      "invalid_dropoff_zone_rows": 957595,
      "nonpositive_distance_rows": 2557,
      "distance_over_100_rows": 1773,
      "negative_fare_rows": 5669,
      "fare_over_500_rows": 590
    },
    {
      "source": "hvfhv",
      "month": "2026-04",
      "raw_record_count": 20995953,
      "outside_month_rows": 0,
      "nonpositive_duration_rows": 29,
      "duration_over_24h_rows": 0,
      "invalid_pickup_zone_rows": 6585,
      "invalid_dropoff_zone_rows": 935999,
      "nonpositive_distance_rows": 1857,
      "distance_over_100_rows": 1555,
      "negative_fare_rows": 5436,
      "fare_over_500_rows": 595
    },
    {
      "source": "yellow",
      "month": "2025-01",
      "raw_record_count": 3475226,
      "outside_month_rows": 22,
      "nonpositive_duration_rows": 2051,
      "duration_over_24h_rows": 20,
      "invalid_pickup_zone_rows": 9555,
      "invalid_dropoff_zone_rows": 24126,
      "nonpositive_distance_rows": 90893,
      "distance_over_100_rows": 162,
      "negative_fare_rows": 144118,
      "fare_over_500_rows": 55
    },
    {
      "source": "yellow",
      "month": "2025-02",
      "raw_record_count": 3577543,
      "outside_month_rows": 31,
      "nonpositive_duration_rows": 5164,
      "duration_over_24h_rows": 16,
      "invalid_pickup_zone_rows": 8694,
      "invalid_dropoff_zone_rows": 21383,
      "nonpositive_distance_rows": 99771,
      "distance_over_100_rows": 172,
      "negative_fare_rows": 182655,
      "fare_over_500_rows": 45
    },
    {
      "source": "yellow",
      "month": "2025-03",
      "raw_record_count": 4145257,
      "outside_month_rows": 33,
      "nonpositive_duration_rows": 22280,
      "duration_over_24h_rows": 11,
      "invalid_pickup_zone_rows": 9312,
      "invalid_dropoff_zone_rows": 24301,
      "nonpositive_distance_rows": 103722,
      "distance_over_100_rows": 214,
      "negative_fare_rows": 208724,
      "fare_over_500_rows": 46
    },
    {
      "source": "yellow",
      "month": "2025-04",
      "raw_record_count": 3970553,
      "outside_month_rows": 7,
      "nonpositive_duration_rows": 34769,
      "duration_over_24h_rows": 25,
      "invalid_pickup_zone_rows": 9068,
      "invalid_dropoff_zone_rows": 24998,
      "nonpositive_distance_rows": 91439,
      "distance_over_100_rows": 306,
      "negative_fare_rows": 186720,
      "fare_over_500_rows": 60
    },
    {
      "source": "yellow",
      "month": "2025-05",
      "raw_record_count": 4591845,
      "outside_month_rows": 24,
      "nonpositive_duration_rows": 64272,
      "duration_over_24h_rows": 26,
      "invalid_pickup_zone_rows": 9767,
      "invalid_dropoff_zone_rows": 30431,
      "nonpositive_distance_rows": 141121,
      "distance_over_100_rows": 370,
      "negative_fare_rows": 325266,
      "fare_over_500_rows": 87
    },
    {
      "source": "yellow",
      "month": "2025-06",
      "raw_record_count": 4322960,
      "outside_month_rows": 20,
      "nonpositive_duration_rows": 68583,
      "duration_over_24h_rows": 20,
      "invalid_pickup_zone_rows": 8699,
      "invalid_dropoff_zone_rows": 29415,
      "nonpositive_distance_rows": 134896,
      "distance_over_100_rows": 264,
      "negative_fare_rows": 275565,
      "fare_over_500_rows": 88
    },
    {
      "source": "yellow",
      "month": "2025-07",
      "raw_record_count": 3898963,
      "outside_month_rows": 7,
      "nonpositive_duration_rows": 56064,
      "duration_over_24h_rows": 31,
      "invalid_pickup_zone_rows": 8492,
      "invalid_dropoff_zone_rows": 28476,
      "nonpositive_distance_rows": 123774,
      "distance_over_100_rows": 274,
      "negative_fare_rows": 247088,
      "fare_over_500_rows": 93
    },
    {
      "source": "yellow",
      "month": "2025-08",
      "raw_record_count": 3574091,
      "outside_month_rows": 17,
      "nonpositive_duration_rows": 47833,
      "duration_over_24h_rows": 45,
      "invalid_pickup_zone_rows": 7821,
      "invalid_dropoff_zone_rows": 28861,
      "nonpositive_distance_rows": 105184,
      "distance_over_100_rows": 245,
      "negative_fare_rows": 261191,
      "fare_over_500_rows": 108
    },
    {
      "source": "yellow",
      "month": "2025-09",
      "raw_record_count": 4251015,
      "outside_month_rows": 7,
      "nonpositive_duration_rows": 57179,
      "duration_over_24h_rows": 37,
      "invalid_pickup_zone_rows": 8333,
      "invalid_dropoff_zone_rows": 28415,
      "nonpositive_distance_rows": 124483,
      "distance_over_100_rows": 214,
      "negative_fare_rows": 252718,
      "fare_over_500_rows": 73
    },
    {
      "source": "yellow",
      "month": "2025-10",
      "raw_record_count": 4428699,
      "outside_month_rows": 13,
      "nonpositive_duration_rows": 67968,
      "duration_over_24h_rows": 35,
      "invalid_pickup_zone_rows": 8606,
      "invalid_dropoff_zone_rows": 29362,
      "nonpositive_distance_rows": 125599,
      "distance_over_100_rows": 229,
      "negative_fare_rows": 321307,
      "fare_over_500_rows": 53
    },
    {
      "source": "yellow",
      "month": "2025-11",
      "raw_record_count": 4181444,
      "outside_month_rows": 24,
      "nonpositive_duration_rows": 62120,
      "duration_over_24h_rows": 42,
      "invalid_pickup_zone_rows": 8097,
      "invalid_dropoff_zone_rows": 27341,
      "nonpositive_distance_rows": 109420,
      "distance_over_100_rows": 223,
      "negative_fare_rows": 395093,
      "fare_over_500_rows": 74
    },
    {
      "source": "yellow",
      "month": "2025-12",
      "raw_record_count": 4305006,
      "outside_month_rows": 9,
      "nonpositive_duration_rows": 58021,
      "duration_over_24h_rows": 44,
      "invalid_pickup_zone_rows": 7691,
      "invalid_dropoff_zone_rows": 28829,
      "nonpositive_distance_rows": 152656,
      "distance_over_100_rows": 197,
      "negative_fare_rows": 48175,
      "fare_over_500_rows": 62
    },
    {
      "source": "yellow",
      "month": "2026-01",
      "raw_record_count": 3724889,
      "outside_month_rows": 7,
      "nonpositive_duration_rows": 45070,
      "duration_over_24h_rows": 35,
      "invalid_pickup_zone_rows": 5996,
      "invalid_dropoff_zone_rows": 22409,
      "nonpositive_distance_rows": 125738,
      "distance_over_100_rows": 162,
      "negative_fare_rows": 39463,
      "fare_over_500_rows": 59
    },
    {
      "source": "yellow",
      "month": "2026-02",
      "raw_record_count": 3399866,
      "outside_month_rows": 16,
      "nonpositive_duration_rows": 40598,
      "duration_over_24h_rows": 37,
      "invalid_pickup_zone_rows": 5085,
      "invalid_dropoff_zone_rows": 19446,
      "nonpositive_distance_rows": 123250,
      "distance_over_100_rows": 172,
      "negative_fare_rows": 26721,
      "fare_over_500_rows": 52
    },
    {
      "source": "yellow",
      "month": "2026-03",
      "raw_record_count": 3952451,
      "outside_month_rows": 19,
      "nonpositive_duration_rows": 49133,
      "duration_over_24h_rows": 28,
      "invalid_pickup_zone_rows": 6299,
      "invalid_dropoff_zone_rows": 20972,
      "nonpositive_distance_rows": 121210,
      "distance_over_100_rows": 161,
      "negative_fare_rows": 20724,
      "fare_over_500_rows": 51
    },
    {
      "source": "yellow",
      "month": "2026-04",
      "raw_record_count": 3800664,
      "outside_month_rows": 12,
      "nonpositive_duration_rows": 18935,
      "duration_over_24h_rows": 21,
      "invalid_pickup_zone_rows": 6057,
      "invalid_dropoff_zone_rows": 20458,
      "nonpositive_distance_rows": 93150,
      "distance_over_100_rows": 136,
      "negative_fare_rows": 14328,
      "fare_over_500_rows": 65
    }
  ],
  "cleaning_rules": {
    "time_clean": "pickup month equals file month; dropoff is after pickup; duration is between 0 and 24 hours",
    "zone_metrics": "pickup/dropoff metrics require the corresponding LocationID to exist in taxi_zones.geojson",
    "od_routes": "both pickup and dropoff LocationID must exist in taxi_zones.geojson and pickup != dropoff",
    "fare_metrics": "fare values below 0 are excluded from fare_sum and avg_fare denominators",
    "distance_metrics": "distance values less than or equal to 0 are excluded from distance_sum and avg_distance denominators"
  }
}